{"incidents":[{"text":"First half","homeScore":0,"awayScore":0,"isLive":true,"time":45,"addedTime":999,"reversedPeriodTime":1,"incidentType":"period"},{"playerIn":{"name":"Luciano Lollo","slug":"luciano-lollo","shortName":"L. Lollo","position":"D","jerseyNumber":"26","userCount":44,"id":249009,"marketValueCurrency":"EUR","dateOfBirthTimestamp":543974400},"playerOut":{"name":"Federico Fernández","slug":"federico-fernandez","shortName":"F. Fernández","position":"D","jerseyNumber":"6","userCount":284,"id":38393,"marketValueCurrency":"EUR","dateOfBirthTimestamp":604022400,"fieldTranslations":{"nameTranslation":{"ar":"فيرنانديز, فيديريكو"},"shortNameTranslation":{"ar":"ف. فيرنانديز"}}},"id":122886621,"time":42,"timeSeconds":2510,"injury":false,"isHome":true,"incidentClass":"regular","reversedPeriodTime":4,"reversedPeriodTimeSeconds":190,"incidentType":"substitution"},{"player":{"name":"Enzo Pérez","slug":"enzo-perez","shortName":"E. Pérez","position":"M","jerseyNumber":"22","userCount":627,"id":33958,"marketValueCurrency":"EUR","dateOfBirthTimestamp":509414400},"reason":"Foul","rescinded":false,"id":121447586,"time":21,"timeSeconds":1238,"isHome":true,"incidentClass":"yellow","reversedPeriodTime":25,"reversedPeriodTimeSeconds":1462,"incidentType":"card"}]}