{"incidents":[{"text":"HT","homeScore":0,"awayScore":0,"isLive":false,"time":45,"addedTime":999,"reversedPeriodTime":1,"incidentType":"period"},{"player":{"name":"Rodrigo Atencio","firstName":"Rodrigo Atencio","lastName":"","slug":"atencio-rodrigo","shortName":"R. Atencio","position":"M","jerseyNumber":"8","userCount":97,"id":1199246,"marketValueCurrency":"EUR","dateOfBirthTimestamp":1025395200},"reason":"Foul","rescinded":false,"id":121436991,"time":45,"timeSeconds":2660,"isHome":true,"incidentClass":"yellow","reversedPeriodTime":1,"reversedPeriodTimeSeconds":40,"incidentType":"card"},{"length":1,"time":45,"addedTime":0,"reversedPeriodTime":1,"incidentType":"injuryTime"},{"player":{"name":"Guido Mainero","slug":"guido-mainero","shortName":"G. Mainero","position":"M","jerseyNumber":"7","userCount":27,"id":895232,"marketValueCurrency":"EUR","dateOfBirthTimestamp":795916800},"reason":"Foul","rescinded":false,"id":121436966,"time":35,"timeSeconds":2051,"isHome":false,"incidentClass":"yellow","reversedPeriodTime":11,"reversedPeriodTimeSeconds":649,"incidentType":"card"}]}