{"incidents":[{"text":"First half","homeScore":2,"awayScore":0,"isLive":true,"time":45,"addedTime":999,"timeSeconds":2700,"reversedPeriodTime":1,"reversedPeriodTimeSeconds":0,"incidentType":"period"},{"homeScore":2,"awayScore":0,"player":{"name":"Juan Miritello","slug":"juan-miritello","shortName":"J. Miritello","position":"F","jerseyNumber":"9","height":182,"userCount":182,"id":1003721,"marketValueCurrency":"EUR","dateOfBirthTimestamp":918432000},"period":"period1","footballPassingNetworkAction":[],"id":188156497,"time":15,"timeSeconds":878,"isHome":true,"incidentClass":"regular","reversedPeriodTime":31,"reversedPeriodTimeSeconds":1822,"incidentType":"goal"},{"from":"heading","homeScore":1,"awayScore":0,"player":{"name":"Juan Miritello","slug":"juan-miritello","shortName":"J. Miritello","position":"F","jerseyNumber":"9","height":182,"userCount":182,"id":1003721,"marketValueCurrency":"EUR","dateOfBirthTimestamp":918432000},"assist1":{"name":"Aaron Molinas","slug":"aaron-molinas","shortName":"A. Molinas","position":"M","jerseyNumber":"16","height":175,"userCount":388,"id":1022257,"marketValueCurrency":"EUR","dateOfBirthTimestamp":965174400},"period":"period1","footballPassingNetworkAction":[],"id":188156456,"time":12,"timeSeconds":670,"isHome":true,"incidentClass":"regular","reversedPeriodTime":34,"reversedPeriodTimeSeconds":2030,"incidentType":"goal"}],"home":{"goalkeeperColor":{"primary":"2a3e8a","number":"f2f2f2","outline":"2a3e8a","fancyNumber":"ffffff"},"playerColor":{"primary":"ffff00","number":"49af12","outline":"ffff00","fancyNumber":"222226"}},"away":{"goalkeeperColor":{"primary":"26dcd2","number":"ffffff","outline":"26dcd2","fancyNumber":"222226"},"playerColor":{"primary":"004080","number":"d9e0d8","outline":"004080","fancyNumber":"ffffff"}}}