{"incidents":[{"text":"FT","homeScore":0,"awayScore":1,"isLive":false,"time":90,"addedTime":999,"timeSeconds":5400,"reversedPeriodTime":1,"reversedPeriodTimeSeconds":0,"incidentType":"period"},{"player":{"name":"Elías Pereyra","slug":"elias-pereyra","shortName":"E. Pereyra","position":"D","jerseyNumber":"21","height":172,"userCount":36,"id":922450,"marketValueCurrency":"EUR","dateOfBirthTimestamp":919036800},"playerName":"Elías Pereyra","reason":"Foul","rescinded":false,"id":121614505,"time":90,"addedTime":3,"isHome":false,"incidentClass":"yellow","reversedPeriodTime":1,"incidentType":"card"},{"length":6,"time":90,"addedTime":0,"reversedPeriodTime":1,"incidentType":"injuryTime"},{"playerIn":{"name":"Mateo Mendoza","firstName":"Mateo Mendoza","lastName":"","slug":"mateo-mendoza","shortName":"M. Mendoza","position":"D","jerseyNumber":"26","height":181,"userCount":9,"id":1467092,"marketValueCurrency":"EUR","dateOfBirthTimestamp":1100995200},"playerOut":{"name":"Santino Andino","firstName":"Santino Andino","slug":"santino-andino","shortName":"S. Andino","position":"M","jerseyNumber":"27","userCount":11,"id":1937592,"marketValueCurrency":"EUR","dateOfBirthTimestamp":1130198400},"id":123140206,"time":88,"injury":true,"isHome":false,"incidentClass":"injury","reversedPeriodTime":3,"incidentType":"substitution"},{"player":{"name":"Yonatan Cabral","slug":"yonatan-cabral","shortName":"Y. Cabral","position":"D","jerseyNumber":"20","height":188,"userCount":23,"id":385318,"marketValueCurrency":"EUR","dateOfBirthTimestamp":705456000},"playerName":"Yonatan Cabral","reason":"Foul","rescinded":false,"id":121614458,"time":86,"isHome":true,"incidentClass":"yellow","reversedPeriodTime":5,"incidentType":"card"},{"confirmed":true,"player":{"name":"Salomón Rodríguez","firstName":"","lastName":"","slug":"salomon-rodriguez","shortName":"S. Rodríguez","position":"F","jerseyNumber":"19","height":186,"userCount":392,"id":1020191,"marketValueCurrency":"EUR","dateOfBirthTimestamp":950659200},"isHome":false,"id":28568,"time":83,"incidentClass":"penaltyNotAwarded","reversedPeriodTime":8,"incidentType":"varDecision"},{"playerIn":{"name":"Daniel Barrea","firstName":"Daniel Barrea","lastName":"","slug":"barrea-daniel","shortName":"D. Barrea","position":"F","jerseyNumber":"36","height":183,"userCount":55,"id":1183778,"marketValueCurrency":"EUR","dateOfBirthTimestamp":995760000},"playerOut":{"name":"Bruno Leyes","firstName":"","lastName":"","slug":"leyes-bruno","shortName":"B. Leyes","position":"M","jerseyNumber":"5","height":173,"userCount":55,"id":1130268,"marketValueCurrency":"EUR","dateOfBirthTimestamp":1004400000},"id":123140176,"time":79,"injury":false,"isHome":false,"incidentClass":"regular","reversedPeriodTime":12,"incidentType":"substitution"},{"playerIn":{"name":"Vicente Poggi","firstName":"","lastName":"","slug":"poggi-vicente","shortName":"V. Poggi","position":"M","jerseyNumber":"25","height":171,"userCount":209,"id":1020066,"marketValueCurrency":"EUR","dateOfBirthTimestamp":1026345600},"playerOut":{"name":"Facundo Altamira","slug":"altamira-facundo","shortName":"F. Altamira","position":"M","jerseyNumber":"41","height":183,"userCount":47,"id":1134768,"marketValueCurrency":"EUR","dateOfBirthTimestamp":996796800},"id":123140175,"time":78,"injury":false,"isHome":false,"incidentClass":"regular","reversedPeriodTime":13,"incidentType":"substitution"},{"playerIn":{"name":"Franco Troyansky","firstName":"","lastName":"","slug":"franco-troyansky","shortName":"F. Troyansky","position":"F","jerseyNumber":"33","height":175,"userCount":84,"id":859990,"marketValueCurrency":"EUR","dateOfBirthTimestamp":857606400},"playerOut":{"name":"Matias Abaldo","firstName":"","lastName":"","slug":"abaldo-matias","shortName":"M. Abaldo","position":"M","jerseyNumber":"9","height":172,"userCount":513,"id":1177402,"marketValueCurrency":"EUR","dateOfBirthTimestamp":1080864000},"id":123140159,"time":74,"injury":false,"isHome":true,"incidentClass":"regular","reversedPeriodTime":17,"incidentType":"substitution"},{"player":{"name":"David Zalazar","slug":"david-zalazar","shortName":"D. Zalazar","position":"F","jerseyNumber":"11","height":177,"userCount":93,"id":1017422,"marketValueCurrency":"EUR","dateOfBirthTimestamp":1020902400},"playerName":"David Zalazar","reason":"Argument","rescinded":false,"id":121614453,"time":72,"isHome":true,"incidentClass":"yellow","reversedPeriodTime":19,"incidentType":"card"},{"playerIn":{"name":"Nicolás Fernández","slug":"nicolas-fernandez","shortName":"N. Fernández","position":"M","jerseyNumber":"13","height":178,"userCount":109,"id":846419,"marketValueCurrency":"EUR","dateOfBirthTimestamp":888796800},"playerOut":{"name":"Juan Perez","firstName":"Juan Perez","lastName":"","slug":"perez-juan","shortName":"J. Perez","position":"M","jerseyNumber":"50","userCount":59,"id":1470460,"marketValueCurrency":"EUR","dateOfBirthTimestamp":1090713600},"id":123140148,"time":69,"injury":false,"isHome":false,"incidentClass":"regular","reversedPeriodTime":22,"incidentType":"substitution"},{"playerIn":{"name":"Fabricio Corbalan","firstName":"Fabricio Corbalan","slug":"fabricio-corbalan","shortName":"F. Corbalan","position":"D","jerseyNumber":"28","height":170,"userCount":5,"id":1893227,"marketValueCurrency":"EUR","dateOfBirthTimestamp":1064793600},"playerOut":{"name":"Juan Pintado","firstName":"","lastName":"","slug":"juan-pintado","shortName":"J. Pintado","position":"D","jerseyNumber":"15","height":178,"userCount":81,"id":805330,"marketValueCurrency":"EUR","dateOfBirthTimestamp":870048000},"id":123140113,"time":64,"injury":true,"isHome":true,"incidentClass":"injury","reversedPeriodTime":27,"incidentType":"substitution"},{"homeScore":0,"awayScore":1,"player":{"name":"Salomón Rodríguez","firstName":"","lastName":"","slug":"salomon-rodriguez","shortName":"S. Rodríguez","position":"F","jerseyNumber":"19","height":186,"userCount":392,"id":1020191,"marketValueCurrency":"EUR","dateOfBirthTimestamp":950659200},"footballPassingNetworkAction":[{"player":{"name":"Franco Petroli","slug":"franco-petroli","shortName":"F. Petroli","position":"G","jerseyNumber":"1","height":187,"userCount":128,"id":822590,"marketValueCurrency":"EUR","dateOfBirthTimestamp":897523200},"eventType":"pass","time":50,"playerCoordinates":{"x":88.7,"y":49.8},"passEndCoordinates":{"x":60.8,"y":10.3}},{"player":{"name":"Santino Andino","firstName":"Santino Andino","slug":"santino-andino","shortName":"S. Andino","position":"M","jerseyNumber":"27","userCount":11,"id":1937592,"marketValueCurrency":"EUR","dateOfBirthTimestamp":1130198400},"eventType":"pass","time":50,"playerCoordinates":{"x":68.8,"y":11.3},"passEndCoordinates":{"x":58.7,"y":32.6}},{"player":{"name":"Juan Perez","firstName":"Juan Perez","lastName":"","slug":"perez-juan","shortName":"J. Perez","position":"M","jerseyNumber":"50","userCount":59,"id":1470460,"marketValueCurrency":"EUR","dateOfBirthTimestamp":1090713600},"eventType":"pass","time":50,"playerCoordinates":{"x":58.9,"y":31},"passEndCoordinates":{"x":44.4,"y":32.5}},{"player":{"name":"Salomón Rodríguez","firstName":"","lastName":"","slug":"salomon-rodriguez","shortName":"S. Rodríguez","position":"F","jerseyNumber":"19","height":186,"userCount":392,"id":1020191,"marketValueCurrency":"EUR","dateOfBirthTimestamp":950659200},"eventType":"pass","time":50,"playerCoordinates":{"x":44.3,"y":32.1},"passEndCoordinates":{"x":44.5,"y":19.8}},{"player":{"name":"Santino Andino","firstName":"Santino Andino","slug":"santino-andino","shortName":"S. Andino","position":"M","jerseyNumber":"27","userCount":11,"id":1937592,"marketValueCurrency":"EUR","dateOfBirthTimestamp":1130198400},"eventType":"ball-movement","time":51,"playerCoordinates":{"x":44.5,"y":19.8}},{"player":{"name":"Santino Andino","firstName":"Santino Andino","slug":"santino-andino","shortName":"S. Andino","position":"M","jerseyNumber":"27","userCount":11,"id":1937592,"marketValueCurrency":"EUR","dateOfBirthTimestamp":1130198400},"eventType":"save","time":51,"playerCoordinates":{"x":9.9,"y":24.6},"goalShotCoordinates":{"x":0,"y":50.9},"goalMouthCoordinates":{"x":54.84,"y":80}},{"player":{"name":"Salomón Rodríguez","firstName":"","lastName":"","slug":"salomon-rodriguez","shortName":"S. Rodríguez","position":"F","jerseyNumber":"19","height":186,"userCount":392,"id":1020191,"marketValueCurrency":"EUR","dateOfBirthTimestamp":950659200},"eventType":"goal","bodyPart":"right-foot","time":51,"playerCoordinates":{"x":3.5,"y":49.8},"gkCoordinates":{"x":2.5,"y":49.6},"goalShotCoordinates":{"x":0,"y":49.1},"goalMouthCoordinates":{"x":45.16,"y":87.33},"goalkeeper":{"name":"Marcos Ledesma","slug":"marcos-ledesma","shortName":"M. Ledesma","position":"G","jerseyNumber":"13","height":188,"userCount":24,"id":757762,"marketValueCurrency":"EUR","dateOfBirthTimestamp":842745600}}],"id":188057453,"time":51,"isHome":false,"incidentClass":"regular","reversedPeriodTime":40,"incidentType":"goal"},{"playerIn":{"name":"Matías Miranda","slug":"matias-miranda","shortName":"M. Miranda","position":"M","jerseyNumber":"8","height":174,"userCount":48,"id":998283,"marketValueCurrency":"EUR","dateOfBirthTimestamp":957484800},"playerOut":{"name":"Valentín Rodríguez","firstName":"Valentín Rodríguez","lastName":"","slug":"valentin-rodriguez","shortName":"V. Rodríguez","position":"D","jerseyNumber":"26","height":173,"userCount":165,"id":1065975,"marketValueCurrency":"EUR","dateOfBirthTimestamp":992390400},"id":123140027,"time":46,"injury":false,"isHome":true,"incidentClass":"regular","reversedPeriodTime":45,"incidentType":"substitution"},{"playerIn":{"name":"Juan Cruz Esquivel","slug":"juan-cruz-esquivel","shortName":"J. C. Esquivel","position":"F","jerseyNumber":"22","height":173,"userCount":73,"id":981347,"marketValueCurrency":"EUR","dateOfBirthTimestamp":966902400},"playerOut":{"name":"Nicolás Garayalde","slug":"nicolas-garayalde","shortName":"N. Garayalde","position":"M","jerseyNumber":"36","height":183,"userCount":127,"id":1017450,"marketValueCurrency":"EUR","dateOfBirthTimestamp":932515200},"id":123140026,"time":46,"injury":false,"isHome":true,"incidentClass":"regular","reversedPeriodTime":45,"incidentType":"substitution"},{"text":"HT","homeScore":0,"awayScore":0,"isLive":false,"time":45,"addedTime":999,"timeSeconds":2700,"reversedPeriodTime":1,"reversedPeriodTimeSeconds":0,"incidentType":"period"},{"player":{"name":"Federico Rasmussen","slug":"federico-rasmussen","shortName":"F. Rasmussen","position":"D","jerseyNumber":"23","height":191,"userCount":35,"id":932903,"marketValueCurrency":"EUR","dateOfBirthTimestamp":699667200},"playerName":"Federico Rasmussen","reason":"Argument","rescinded":false,"id":121614288,"time":45,"isHome":false,"incidentClass":"yellow","reversedPeriodTime":1,"incidentType":"card"},{"length":4,"time":45,"addedTime":0,"reversedPeriodTime":1,"incidentType":"injuryTime"},{"player":{"name":"Lucas Arce","firstName":"Lucas Arce","lastName":"","slug":"lucas-arce","shortName":"L. Arce","position":"D","jerseyNumber":"4","height":172,"userCount":35,"id":1109302,"marketValueCurrency":"EUR","dateOfBirthTimestamp":871516800},"playerName":"Lucas Arce","reason":"Foul","rescinded":false,"id":121614278,"time":44,"isHome":false,"incidentClass":"yellow","reversedPeriodTime":2,"incidentType":"card"}],"home":{"goalkeeperColor":{"primary":"f028a7","number":"ffffff","outline":"f028a7","fancyNumber":"222226"},"playerColor":{"primary":"ffffff","number":"1b2f44","outline":"ffffff","fancyNumber":"222226"}},"away":{"goalkeeperColor":{"primary":"000000","number":"ffffff","outline":"000000","fancyNumber":"ffffff"},"playerColor":{"primary":"001fd3","number":"ffffff","outline":"001fd3","fancyNumber":"ffffff"}}}