{"incidents":[{"text":"HT","homeScore":0,"awayScore":0,"isLive":false,"time":45,"addedTime":999,"reversedPeriodTime":1,"incidentType":"period"},{"length":2,"time":45,"addedTime":0,"reversedPeriodTime":1,"incidentType":"injuryTime"},{"player":{"name":"Valentino Werro","firstName":"Valentino Werro","lastName":"","slug":"valentino-werro","shortName":"V. Werro","position":"M","userCount":1,"id":1200740},"rescinded":false,"id":121300086,"time":35,"timeSeconds":2074,"isHome":true,"incidentClass":"yellow","reversedPeriodTime":11,"reversedPeriodTimeSeconds":626,"incidentType":"card"},{"playerIn":{"name":"Maximiliano Luayza","firstName":"Maximiliano Luayza","lastName":"","slug":"maximiliano-luayza","shortName":"M. Luayza","position":"M","jerseyNumber":"32","userCount":3,"id":1065604},"playerOut":{"name":"Francisco Funes","slug":"francisco-funes","shortName":"F. Funes","userCount":1,"id":1654396},"id":122643797,"time":33,"injury":false,"isHome":true,"incidentClass":"regular","reversedPeriodTime":13,"incidentType":"substitution"},{"player":{"name":"Matteo Trombini","firstName":"Matteo Trombini","slug":"matteo-trombini","shortName":"M. Trombini","position":"M","jerseyNumber":"34","userCount":4,"id":1185974},"rescinded":false,"id":121300087,"time":32,"timeSeconds":1893,"isHome":false,"incidentClass":"yellow","reversedPeriodTime":14,"reversedPeriodTimeSeconds":807,"incidentType":"card"}]}